MANIFEST.in
README.txt
setup.cfg
setup.py
docs/HISTORY.txt
pcommerce/__init__.py
pcommerce.shipment.swisspost.egg-info/PKG-INFO
pcommerce.shipment.swisspost.egg-info/SOURCES.txt
pcommerce.shipment.swisspost.egg-info/dependency_links.txt
pcommerce.shipment.swisspost.egg-info/entry_points.txt
pcommerce.shipment.swisspost.egg-info/namespace_packages.txt
pcommerce.shipment.swisspost.egg-info/not-zip-safe
pcommerce.shipment.swisspost.egg-info/requires.txt
pcommerce.shipment.swisspost.egg-info/top_level.txt
pcommerce/shipment/__init__.py
pcommerce/shipment/swisspost/__init__.py
pcommerce/shipment/swisspost/configure.zcml
pcommerce/shipment/swisspost/data.py
pcommerce/shipment/swisspost/interfaces.py
pcommerce/shipment/swisspost/plugin.py
pcommerce/shipment/swisspost/browser/__init__.py
pcommerce/shipment/swisspost/browser/base.py
pcommerce/shipment/swisspost/browser/configure.zcml
pcommerce/shipment/swisspost/browser/confirmation.pt
pcommerce/shipment/swisspost/browser/confirmation.py
pcommerce/shipment/swisspost/browser/icon.gif
pcommerce/shipment/swisspost/browser/logo.gif
pcommerce/shipment/swisspost/browser/overview.pt
pcommerce/shipment/swisspost/browser/overview.py
pcommerce/shipment/swisspost/browser/shipment.pt
pcommerce/shipment/swisspost/browser/shipment.py
pcommerce/shipment/swisspost/i18n/pcommerce-de.mo
pcommerce/shipment/swisspost/i18n/pcommerce-de.po
pcommerce/shipment/swisspost/i18n/pcommerce-nl.mo
pcommerce/shipment/swisspost/i18n/pcommerce-nl.po
pcommerce/shipment/swisspost/i18n/pcommerce.pot
pcommerce/shipment/swisspost/profiles/default/metadata.xml
pcommerce/shipment/swisspost/profiles/default/propertiestool.xml