Metadata-Version: 1.0
Name: pcommerce.shipment.swisspost
Version: 1.0b3
Summary: A SwissPost shipment method for PCommerce
Home-page: http://raptus.com
Author: Jan Boehler
Author-email: jboehler@raptus.com
License: GPL
Platform: UNKNOWN
Classifier: Programming Language :: Python
Classifier: Topic :: Software Development :: Libraries :: Python Modules
